cvhough_sdk/__init__.py
cvhough_sdk/detector.py
cvhough_sdk/main.py
cvhough_sdk/models/best.pt
cvhough_hui-1.0.3.dist-info/METADATA
cvhough_hui-1.0.3.dist-info/WHEEL
cvhough_hui-1.0.3.dist-info/entry_points.txt
cvhough_hui-1.0.3.dist-info/top_level.txt
cvhough_hui-1.0.3.dist-info/RECORD
