Metadata-Version: 2.4
Name: cvhough-hui
Version: 1.0.3
Summary: 基于YOLO和Hough变换的灰色圆形检测SDK
Home-page: https://github.com/ruantong/cvhough-hui
Author: ruantong
Author-email: ypwucu@isoftstone.com
Project-URL: Bug Reports, https://github.com/cvhough/cvhough-hui/issues
Project-URL: Source, https://github.com/cvhough/cvhough-hui
Project-URL: Documentation, https://cvhough-hui.readthedocs.io/
Keywords: computer vision,object detection,circle detection,YOLO,Hough transform,image processing,machine learning,deep learning
Classifier: Development Status :: 4 - Beta
Classifier: Intended Audience :: Developers
Classifier: License :: OSI Approved :: MIT License
Classifier: Operating System :: OS Independent
Classifier: Programming Language :: Python :: 3
Classifier: Programming Language :: Python :: 3.7
Classifier: Programming Language :: Python :: 3.8
Classifier: Programming Language :: Python :: 3.9
Classifier: Programming Language :: Python :: 3.10
Classifier: Programming Language :: Python :: 3.11
Classifier: Topic :: Scientific/Engineering :: Image Processing
Classifier: Topic :: Scientific/Engineering :: Artificial Intelligence
Classifier: Topic :: Software Development :: Libraries :: Python Modules
Requires-Python: >=3.7
Requires-Dist: opencv-python>=4.5.0
Requires-Dist: numpy>=1.19.0
Requires-Dist: torch>=1.9.0
Requires-Dist: ultralytics>=8.0.0
Provides-Extra: dev
Requires-Dist: pytest>=6.0; extra == "dev"
Requires-Dist: pytest-cov>=2.0; extra == "dev"
Requires-Dist: black>=21.0; extra == "dev"
Requires-Dist: flake8>=3.8; extra == "dev"
Provides-Extra: gpu
Requires-Dist: torch>=1.9.0; extra == "gpu"
Dynamic: author
Dynamic: author-email
Dynamic: classifier
Dynamic: description
Dynamic: description-content-type
Dynamic: home-page
Dynamic: keywords
Dynamic: project-url
Dynamic: provides-extra
Dynamic: requires-dist
Dynamic: requires-python
Dynamic: summary
